3designs-1.0.1.dist-info/licenses/LICENSE
mcp_server/__init__.py
mcp_server/server.py
3designs-1.0.1.dist-info/METADATA
3designs-1.0.1.dist-info/WHEEL
3designs-1.0.1.dist-info/entry_points.txt
3designs-1.0.1.dist-info/top_level.txt
3designs-1.0.1.dist-info/RECORD
