Metadata-Version: 2.4
Name: 3designs
Version: 1.0.1
Summary: A FastMCP server for 3designs SwiftUI development assistance.
Author-email: Anton <anton@mimecam.com>
License-Expression: MIT
Project-URL: Homepage, https://github.com/mimeCam/mcp-3designs-stdio
Project-URL: Bug Tracker, https://github.com/mimeCam/mcp-3designs-stdio/discussions
Classifier: Programming Language :: Python :: 3.10
Classifier: Operating System :: OS Independent
Classifier: Intended Audience :: Developers
Requires-Python: >=3.10
License-File: LICENSE
Requires-Dist: fastmcp
Requires-Dist: requests
Dynamic: license-file
